{
  "updatedAt": "2026-04-12T14:06:18.944Z",
  "source": "izmir-open-data-js / ESHOT getHareketSaatleri",
  "hatNo": "816",
  "total": 62,
  "saatler": [
    {
      "_id": 85970,
      "HAT_NO": 816,
      "TARIFE_ID": 1,
      "GIDIS_SAATI": "06:00",
      "DONUS_SAATI": "06:40",
      "SIRA": 1,
      "GIDIS_ENGELLI_DESTEGI": "True",
      "DONUS_ENGELLI_DESTEGI": "True",
      "BISIKLETLI_GIDIS": "True",
      "BISIKLETLI_DONUS": "True",
      "GIDIS_ELEKTRIKLI_OTOBUS": "False",
      "DONUS_ELEKTRIKLI_OTOBUS": "False"
    },
    {
      "_id": 85971,
      "HAT_NO": 816,
      "TARIFE_ID": 1,
      "GIDIS_SAATI": "06:45",
      "DONUS_SAATI": "08:15",
      "SIRA": 2,
      "GIDIS_ENGELLI_DESTEGI": "True",
      "DONUS_ENGELLI_DESTEGI": "True",
      "BISIKLETLI_GIDIS": "False",
      "BISIKLETLI_DONUS": "True",
      "GIDIS_ELEKTRIKLI_OTOBUS": "False",
      "DONUS_ELEKTRIKLI_OTOBUS": "False"
    },
    {
      "_id": 85972,
      "HAT_NO": 816,
      "TARIFE_ID": 1,
      "GIDIS_SAATI": "07:25",
      "DONUS_SAATI": "10:05",
      "SIRA": 3,
      "GIDIS_ENGELLI_DESTEGI": "True",
      "DONUS_ENGELLI_DESTEGI": "True",
      "BISIKLETLI_GIDIS": "True",
      "BISIKLETLI_DONUS": "True",
      "GIDIS_ELEKTRIKLI_OTOBUS": "False",
      "DONUS_ELEKTRIKLI_OTOBUS": "False"
    },
    {
      "_id": 85973,
      "HAT_NO": 816,
      "TARIFE_ID": 1,
      "GIDIS_SAATI": "09:05",
      "DONUS_SAATI": "12:05",
      "SIRA": 4,
      "GIDIS_ENGELLI_DESTEGI": "True",
      "DONUS_ENGELLI_DESTEGI": "True",
      "BISIKLETLI_GIDIS": "True",
      "BISIKLETLI_DONUS": "True",
      "GIDIS_ELEKTRIKLI_OTOBUS": "False",
      "DONUS_ELEKTRIKLI_OTOBUS": "False"
    },
    {
      "_id": 85974,
      "HAT_NO": 816,
      "TARIFE_ID": 1,
      "GIDIS_SAATI": "11:05",
      "DONUS_SAATI": "14:05",
      "SIRA": 5,
      "GIDIS_ENGELLI_DESTEGI": "True",
      "DONUS_ENGELLI_DESTEGI": "True",
      "BISIKLETLI_GIDIS": "True",
      "BISIKLETLI_DONUS": "True",
      "GIDIS_ELEKTRIKLI_OTOBUS": "False",
      "DONUS_ELEKTRIKLI_OTOBUS": "False"
    },
    {
      "_id": 85975,
      "HAT_NO": 816,
      "TARIFE_ID": 1,
      "GIDIS_SAATI": "13:05",
      "DONUS_SAATI": "16:05",
      "SIRA": 6,
      "GIDIS_ENGELLI_DESTEGI": "True",
      "DONUS_ENGELLI_DESTEGI": "True",
      "BISIKLETLI_GIDIS": "True",
      "BISIKLETLI_DONUS": "True",
      "GIDIS_ELEKTRIKLI_OTOBUS": "False",
      "DONUS_ELEKTRIKLI_OTOBUS": "False"
    },
    {
      "_id": 85976,
      "HAT_NO": 816,
      "TARIFE_ID": 1,
      "GIDIS_SAATI": "15:05",
      "DONUS_SAATI": "18:05",
      "SIRA": 7,
      "GIDIS_ENGELLI_DESTEGI": "True",
      "DONUS_ENGELLI_DESTEGI": "True",
      "BISIKLETLI_GIDIS": "True",
      "BISIKLETLI_DONUS": "True",
      "GIDIS_ELEKTRIKLI_OTOBUS": "False",
      "DONUS_ELEKTRIKLI_OTOBUS": "False"
    },
    {
      "_id": 85977,
      "HAT_NO": 816,
      "TARIFE_ID": 1,
      "GIDIS_SAATI": "17:05",
      "DONUS_SAATI": "",
      "SIRA": 8,
      "GIDIS_ENGELLI_DESTEGI": "True",
      "DONUS_ENGELLI_DESTEGI": "False",
      "BISIKLETLI_GIDIS": "True",
      "BISIKLETLI_DONUS": "False",
      "GIDIS_ELEKTRIKLI_OTOBUS": "False",
      "DONUS_ELEKTRIKLI_OTOBUS": "False"
    },
    {
      "_id": 85978,
      "HAT_NO": 816,
      "TARIFE_ID": 1,
      "GIDIS_SAATI": "19:05",
      "DONUS_SAATI": "",
      "SIRA": 9,
      "GIDIS_ENGELLI_DESTEGI": "True",
      "DONUS_ENGELLI_DESTEGI": "False",
      "BISIKLETLI_GIDIS": "True",
      "BISIKLETLI_DONUS": "False",
      "GIDIS_ELEKTRIKLI_OTOBUS": "False",
      "DONUS_ELEKTRIKLI_OTOBUS": "False"
    },
    {
      "_id": 85979,
      "HAT_NO": 816,
      "TARIFE_ID": 1,
      "GIDIS_SAATI": "06:00",
      "DONUS_SAATI": "06:40",
      "SIRA": 1,
      "GIDIS_ENGELLI_DESTEGI": "True",
      "DONUS_ENGELLI_DESTEGI": "True",
      "BISIKLETLI_GIDIS": "True",
      "BISIKLETLI_DONUS": "True",
      "GIDIS_ELEKTRIKLI_OTOBUS": "False",
      "DONUS_ELEKTRIKLI_OTOBUS": "False"
    },
    {
      "_id": 85980,
      "HAT_NO": 816,
      "TARIFE_ID": 1,
      "GIDIS_SAATI": "06:45",
      "DONUS_SAATI": "08:15",
      "SIRA": 2,
      "GIDIS_ENGELLI_DESTEGI": "True",
      "DONUS_ENGELLI_DESTEGI": "True",
      "BISIKLETLI_GIDIS": "False",
      "BISIKLETLI_DONUS": "True",
      "GIDIS_ELEKTRIKLI_OTOBUS": "False",
      "DONUS_ELEKTRIKLI_OTOBUS": "False"
    },
    {
      "_id": 85981,
      "HAT_NO": 816,
      "TARIFE_ID": 1,
      "GIDIS_SAATI": "07:25",
      "DONUS_SAATI": "10:05",
      "SIRA": 3,
      "GIDIS_ENGELLI_DESTEGI": "True",
      "DONUS_ENGELLI_DESTEGI": "True",
      "BISIKLETLI_GIDIS": "True",
      "BISIKLETLI_DONUS": "True",
      "GIDIS_ELEKTRIKLI_OTOBUS": "False",
      "DONUS_ELEKTRIKLI_OTOBUS": "False"
    },
    {
      "_id": 85982,
      "HAT_NO": 816,
      "TARIFE_ID": 1,
      "GIDIS_SAATI": "09:05",
      "DONUS_SAATI": "12:05",
      "SIRA": 4,
      "GIDIS_ENGELLI_DESTEGI": "True",
      "DONUS_ENGELLI_DESTEGI": "True",
      "BISIKLETLI_GIDIS": "True",
      "BISIKLETLI_DONUS": "True",
      "GIDIS_ELEKTRIKLI_OTOBUS": "False",
      "DONUS_ELEKTRIKLI_OTOBUS": "False"
    },
    {
      "_id": 85983,
      "HAT_NO": 816,
      "TARIFE_ID": 1,
      "GIDIS_SAATI": "11:05",
      "DONUS_SAATI": "14:05",
      "SIRA": 5,
      "GIDIS_ENGELLI_DESTEGI": "True",
      "DONUS_ENGELLI_DESTEGI": "True",
      "BISIKLETLI_GIDIS": "True",
      "BISIKLETLI_DONUS": "True",
      "GIDIS_ELEKTRIKLI_OTOBUS": "False",
      "DONUS_ELEKTRIKLI_OTOBUS": "False"
    },
    {
      "_id": 85984,
      "HAT_NO": 816,
      "TARIFE_ID": 1,
      "GIDIS_SAATI": "13:05",
      "DONUS_SAATI": "16:05",
      "SIRA": 6,
      "GIDIS_ENGELLI_DESTEGI": "True",
      "DONUS_ENGELLI_DESTEGI": "True",
      "BISIKLETLI_GIDIS": "True",
      "BISIKLETLI_DONUS": "True",
      "GIDIS_ELEKTRIKLI_OTOBUS": "False",
      "DONUS_ELEKTRIKLI_OTOBUS": "False"
    },
    {
      "_id": 85985,
      "HAT_NO": 816,
      "TARIFE_ID": 1,
      "GIDIS_SAATI": "15:05",
      "DONUS_SAATI": "18:05",
      "SIRA": 7,
      "GIDIS_ENGELLI_DESTEGI": "True",
      "DONUS_ENGELLI_DESTEGI": "True",
      "BISIKLETLI_GIDIS": "True",
      "BISIKLETLI_DONUS": "True",
      "GIDIS_ELEKTRIKLI_OTOBUS": "False",
      "DONUS_ELEKTRIKLI_OTOBUS": "False"
    },
    {
      "_id": 85986,
      "HAT_NO": 816,
      "TARIFE_ID": 1,
      "GIDIS_SAATI": "17:05",
      "DONUS_SAATI": "",
      "SIRA": 8,
      "GIDIS_ENGELLI_DESTEGI": "True",
      "DONUS_ENGELLI_DESTEGI": "False",
      "BISIKLETLI_GIDIS": "True",
      "BISIKLETLI_DONUS": "False",
      "GIDIS_ELEKTRIKLI_OTOBUS": "False",
      "DONUS_ELEKTRIKLI_OTOBUS": "False"
    },
    {
      "_id": 85987,
      "HAT_NO": 816,
      "TARIFE_ID": 1,
      "GIDIS_SAATI": "19:05",
      "DONUS_SAATI": "",
      "SIRA": 9,
      "GIDIS_ENGELLI_DESTEGI": "True",
      "DONUS_ENGELLI_DESTEGI": "False",
      "BISIKLETLI_GIDIS": "True",
      "BISIKLETLI_DONUS": "False",
      "GIDIS_ELEKTRIKLI_OTOBUS": "False",
      "DONUS_ELEKTRIKLI_OTOBUS": "False"
    },
    {
      "_id": 85988,
      "HAT_NO": 816,
      "TARIFE_ID": 1,
      "GIDIS_SAATI": "06:00",
      "DONUS_SAATI": "06:40",
      "SIRA": 1,
      "GIDIS_ENGELLI_DESTEGI": "True",
      "DONUS_ENGELLI_DESTEGI": "True",
      "BISIKLETLI_GIDIS": "True",
      "BISIKLETLI_DONUS": "True",
      "GIDIS_ELEKTRIKLI_OTOBUS": "False",
      "DONUS_ELEKTRIKLI_OTOBUS": "False"
    },
    {
      "_id": 85989,
      "HAT_NO": 816,
      "TARIFE_ID": 1,
      "GIDIS_SAATI": "06:45",
      "DONUS_SAATI": "08:15",
      "SIRA": 2,
      "GIDIS_ENGELLI_DESTEGI": "True",
      "DONUS_ENGELLI_DESTEGI": "True",
      "BISIKLETLI_GIDIS": "False",
      "BISIKLETLI_DONUS": "True",
      "GIDIS_ELEKTRIKLI_OTOBUS": "False",
      "DONUS_ELEKTRIKLI_OTOBUS": "False"
    },
    {
      "_id": 85990,
      "HAT_NO": 816,
      "TARIFE_ID": 1,
      "GIDIS_SAATI": "07:25",
      "DONUS_SAATI": "10:05",
      "SIRA": 3,
      "GIDIS_ENGELLI_DESTEGI": "True",
      "DONUS_ENGELLI_DESTEGI": "True",
      "BISIKLETLI_GIDIS": "True",
      "BISIKLETLI_DONUS": "True",
      "GIDIS_ELEKTRIKLI_OTOBUS": "False",
      "DONUS_ELEKTRIKLI_OTOBUS": "False"
    },
    {
      "_id": 85991,
      "HAT_NO": 816,
      "TARIFE_ID": 1,
      "GIDIS_SAATI": "09:05",
      "DONUS_SAATI": "12:05",
      "SIRA": 4,
      "GIDIS_ENGELLI_DESTEGI": "True",
      "DONUS_ENGELLI_DESTEGI": "True",
      "BISIKLETLI_GIDIS": "True",
      "BISIKLETLI_DONUS": "True",
      "GIDIS_ELEKTRIKLI_OTOBUS": "False",
      "DONUS_ELEKTRIKLI_OTOBUS": "False"
    },
    {
      "_id": 85992,
      "HAT_NO": 816,
      "TARIFE_ID": 1,
      "GIDIS_SAATI": "11:05",
      "DONUS_SAATI": "14:05",
      "SIRA": 5,
      "GIDIS_ENGELLI_DESTEGI": "True",
      "DONUS_ENGELLI_DESTEGI": "True",
      "BISIKLETLI_GIDIS": "True",
      "BISIKLETLI_DONUS": "True",
      "GIDIS_ELEKTRIKLI_OTOBUS": "False",
      "DONUS_ELEKTRIKLI_OTOBUS": "False"
    },
    {
      "_id": 85993,
      "HAT_NO": 816,
      "TARIFE_ID": 1,
      "GIDIS_SAATI": "13:05",
      "DONUS_SAATI": "16:05",
      "SIRA": 6,
      "GIDIS_ENGELLI_DESTEGI": "True",
      "DONUS_ENGELLI_DESTEGI": "True",
      "BISIKLETLI_GIDIS": "True",
      "BISIKLETLI_DONUS": "True",
      "GIDIS_ELEKTRIKLI_OTOBUS": "False",
      "DONUS_ELEKTRIKLI_OTOBUS": "False"
    },
    {
      "_id": 85994,
      "HAT_NO": 816,
      "TARIFE_ID": 1,
      "GIDIS_SAATI": "15:05",
      "DONUS_SAATI": "18:05",
      "SIRA": 7,
      "GIDIS_ENGELLI_DESTEGI": "True",
      "DONUS_ENGELLI_DESTEGI": "True",
      "BISIKLETLI_GIDIS": "True",
      "BISIKLETLI_DONUS": "True",
      "GIDIS_ELEKTRIKLI_OTOBUS": "False",
      "DONUS_ELEKTRIKLI_OTOBUS": "False"
    },
    {
      "_id": 85995,
      "HAT_NO": 816,
      "TARIFE_ID": 1,
      "GIDIS_SAATI": "17:05",
      "DONUS_SAATI": "",
      "SIRA": 8,
      "GIDIS_ENGELLI_DESTEGI": "True",
      "DONUS_ENGELLI_DESTEGI": "False",
      "BISIKLETLI_GIDIS": "True",
      "BISIKLETLI_DONUS": "False",
      "GIDIS_ELEKTRIKLI_OTOBUS": "False",
      "DONUS_ELEKTRIKLI_OTOBUS": "False"
    },
    {
      "_id": 85996,
      "HAT_NO": 816,
      "TARIFE_ID": 1,
      "GIDIS_SAATI": "19:05",
      "DONUS_SAATI": "",
      "SIRA": 9,
      "GIDIS_ENGELLI_DESTEGI": "True",
      "DONUS_ENGELLI_DESTEGI": "False",
      "BISIKLETLI_GIDIS": "True",
      "BISIKLETLI_DONUS": "False",
      "GIDIS_ELEKTRIKLI_OTOBUS": "False",
      "DONUS_ELEKTRIKLI_OTOBUS": "False"
    },
    {
      "_id": 85997,
      "HAT_NO": 816,
      "TARIFE_ID": 1,
      "GIDIS_SAATI": "06:00",
      "DONUS_SAATI": "06:40",
      "SIRA": 1,
      "GIDIS_ENGELLI_DESTEGI": "True",
      "DONUS_ENGELLI_DESTEGI": "True",
      "BISIKLETLI_GIDIS": "True",
      "BISIKLETLI_DONUS": "True",
      "GIDIS_ELEKTRIKLI_OTOBUS": "False",
      "DONUS_ELEKTRIKLI_OTOBUS": "False"
    },
    {
      "_id": 85998,
      "HAT_NO": 816,
      "TARIFE_ID": 1,
      "GIDIS_SAATI": "06:45",
      "DONUS_SAATI": "08:15",
      "SIRA": 2,
      "GIDIS_ENGELLI_DESTEGI": "True",
      "DONUS_ENGELLI_DESTEGI": "True",
      "BISIKLETLI_GIDIS": "False",
      "BISIKLETLI_DONUS": "True",
      "GIDIS_ELEKTRIKLI_OTOBUS": "False",
      "DONUS_ELEKTRIKLI_OTOBUS": "False"
    },
    {
      "_id": 85999,
      "HAT_NO": 816,
      "TARIFE_ID": 1,
      "GIDIS_SAATI": "07:25",
      "DONUS_SAATI": "10:05",
      "SIRA": 3,
      "GIDIS_ENGELLI_DESTEGI": "True",
      "DONUS_ENGELLI_DESTEGI": "True",
      "BISIKLETLI_GIDIS": "True",
      "BISIKLETLI_DONUS": "True",
      "GIDIS_ELEKTRIKLI_OTOBUS": "False",
      "DONUS_ELEKTRIKLI_OTOBUS": "False"
    },
    {
      "_id": 86000,
      "HAT_NO": 816,
      "TARIFE_ID": 1,
      "GIDIS_SAATI": "09:05",
      "DONUS_SAATI": "12:05",
      "SIRA": 4,
      "GIDIS_ENGELLI_DESTEGI": "True",
      "DONUS_ENGELLI_DESTEGI": "True",
      "BISIKLETLI_GIDIS": "True",
      "BISIKLETLI_DONUS": "True",
      "GIDIS_ELEKTRIKLI_OTOBUS": "False",
      "DONUS_ELEKTRIKLI_OTOBUS": "False"
    },
    {
      "_id": 86001,
      "HAT_NO": 816,
      "TARIFE_ID": 1,
      "GIDIS_SAATI": "11:05",
      "DONUS_SAATI": "14:05",
      "SIRA": 5,
      "GIDIS_ENGELLI_DESTEGI": "True",
      "DONUS_ENGELLI_DESTEGI": "True",
      "BISIKLETLI_GIDIS": "True",
      "BISIKLETLI_DONUS": "True",
      "GIDIS_ELEKTRIKLI_OTOBUS": "False",
      "DONUS_ELEKTRIKLI_OTOBUS": "False"
    },
    {
      "_id": 86002,
      "HAT_NO": 816,
      "TARIFE_ID": 1,
      "GIDIS_SAATI": "13:05",
      "DONUS_SAATI": "16:05",
      "SIRA": 6,
      "GIDIS_ENGELLI_DESTEGI": "True",
      "DONUS_ENGELLI_DESTEGI": "True",
      "BISIKLETLI_GIDIS": "True",
      "BISIKLETLI_DONUS": "True",
      "GIDIS_ELEKTRIKLI_OTOBUS": "False",
      "DONUS_ELEKTRIKLI_OTOBUS": "False"
    },
    {
      "_id": 86003,
      "HAT_NO": 816,
      "TARIFE_ID": 1,
      "GIDIS_SAATI": "15:05",
      "DONUS_SAATI": "18:05",
      "SIRA": 7,
      "GIDIS_ENGELLI_DESTEGI": "True",
      "DONUS_ENGELLI_DESTEGI": "True",
      "BISIKLETLI_GIDIS": "True",
      "BISIKLETLI_DONUS": "True",
      "GIDIS_ELEKTRIKLI_OTOBUS": "False",
      "DONUS_ELEKTRIKLI_OTOBUS": "False"
    },
    {
      "_id": 86004,
      "HAT_NO": 816,
      "TARIFE_ID": 1,
      "GIDIS_SAATI": "17:05",
      "DONUS_SAATI": "",
      "SIRA": 8,
      "GIDIS_ENGELLI_DESTEGI": "True",
      "DONUS_ENGELLI_DESTEGI": "False",
      "BISIKLETLI_GIDIS": "True",
      "BISIKLETLI_DONUS": "False",
      "GIDIS_ELEKTRIKLI_OTOBUS": "False",
      "DONUS_ELEKTRIKLI_OTOBUS": "False"
    },
    {
      "_id": 86005,
      "HAT_NO": 816,
      "TARIFE_ID": 1,
      "GIDIS_SAATI": "19:05",
      "DONUS_SAATI": "",
      "SIRA": 9,
      "GIDIS_ENGELLI_DESTEGI": "True",
      "DONUS_ENGELLI_DESTEGI": "False",
      "BISIKLETLI_GIDIS": "True",
      "BISIKLETLI_DONUS": "False",
      "GIDIS_ELEKTRIKLI_OTOBUS": "False",
      "DONUS_ELEKTRIKLI_OTOBUS": "False"
    },
    {
      "_id": 86006,
      "HAT_NO": 816,
      "TARIFE_ID": 1,
      "GIDIS_SAATI": "06:00",
      "DONUS_SAATI": "06:40",
      "SIRA": 1,
      "GIDIS_ENGELLI_DESTEGI": "True",
      "DONUS_ENGELLI_DESTEGI": "True",
      "BISIKLETLI_GIDIS": "True",
      "BISIKLETLI_DONUS": "True",
      "GIDIS_ELEKTRIKLI_OTOBUS": "False",
      "DONUS_ELEKTRIKLI_OTOBUS": "False"
    },
    {
      "_id": 86007,
      "HAT_NO": 816,
      "TARIFE_ID": 1,
      "GIDIS_SAATI": "06:45",
      "DONUS_SAATI": "08:15",
      "SIRA": 2,
      "GIDIS_ENGELLI_DESTEGI": "True",
      "DONUS_ENGELLI_DESTEGI": "True",
      "BISIKLETLI_GIDIS": "False",
      "BISIKLETLI_DONUS": "True",
      "GIDIS_ELEKTRIKLI_OTOBUS": "False",
      "DONUS_ELEKTRIKLI_OTOBUS": "False"
    },
    {
      "_id": 86008,
      "HAT_NO": 816,
      "TARIFE_ID": 1,
      "GIDIS_SAATI": "07:25",
      "DONUS_SAATI": "10:05",
      "SIRA": 3,
      "GIDIS_ENGELLI_DESTEGI": "True",
      "DONUS_ENGELLI_DESTEGI": "True",
      "BISIKLETLI_GIDIS": "True",
      "BISIKLETLI_DONUS": "True",
      "GIDIS_ELEKTRIKLI_OTOBUS": "False",
      "DONUS_ELEKTRIKLI_OTOBUS": "False"
    },
    {
      "_id": 86009,
      "HAT_NO": 816,
      "TARIFE_ID": 1,
      "GIDIS_SAATI": "09:05",
      "DONUS_SAATI": "12:05",
      "SIRA": 4,
      "GIDIS_ENGELLI_DESTEGI": "True",
      "DONUS_ENGELLI_DESTEGI": "True",
      "BISIKLETLI_GIDIS": "True",
      "BISIKLETLI_DONUS": "True",
      "GIDIS_ELEKTRIKLI_OTOBUS": "False",
      "DONUS_ELEKTRIKLI_OTOBUS": "False"
    },
    {
      "_id": 86010,
      "HAT_NO": 816,
      "TARIFE_ID": 1,
      "GIDIS_SAATI": "11:05",
      "DONUS_SAATI": "14:05",
      "SIRA": 5,
      "GIDIS_ENGELLI_DESTEGI": "True",
      "DONUS_ENGELLI_DESTEGI": "True",
      "BISIKLETLI_GIDIS": "True",
      "BISIKLETLI_DONUS": "True",
      "GIDIS_ELEKTRIKLI_OTOBUS": "False",
      "DONUS_ELEKTRIKLI_OTOBUS": "False"
    },
    {
      "_id": 86011,
      "HAT_NO": 816,
      "TARIFE_ID": 1,
      "GIDIS_SAATI": "13:05",
      "DONUS_SAATI": "16:05",
      "SIRA": 6,
      "GIDIS_ENGELLI_DESTEGI": "True",
      "DONUS_ENGELLI_DESTEGI": "True",
      "BISIKLETLI_GIDIS": "True",
      "BISIKLETLI_DONUS": "True",
      "GIDIS_ELEKTRIKLI_OTOBUS": "False",
      "DONUS_ELEKTRIKLI_OTOBUS": "False"
    },
    {
      "_id": 86012,
      "HAT_NO": 816,
      "TARIFE_ID": 1,
      "GIDIS_SAATI": "15:05",
      "DONUS_SAATI": "18:05",
      "SIRA": 7,
      "GIDIS_ENGELLI_DESTEGI": "True",
      "DONUS_ENGELLI_DESTEGI": "True",
      "BISIKLETLI_GIDIS": "True",
      "BISIKLETLI_DONUS": "True",
      "GIDIS_ELEKTRIKLI_OTOBUS": "False",
      "DONUS_ELEKTRIKLI_OTOBUS": "False"
    },
    {
      "_id": 86013,
      "HAT_NO": 816,
      "TARIFE_ID": 1,
      "GIDIS_SAATI": "17:05",
      "DONUS_SAATI": "",
      "SIRA": 8,
      "GIDIS_ENGELLI_DESTEGI": "True",
      "DONUS_ENGELLI_DESTEGI": "False",
      "BISIKLETLI_GIDIS": "True",
      "BISIKLETLI_DONUS": "False",
      "GIDIS_ELEKTRIKLI_OTOBUS": "False",
      "DONUS_ELEKTRIKLI_OTOBUS": "False"
    },
    {
      "_id": 86014,
      "HAT_NO": 816,
      "TARIFE_ID": 1,
      "GIDIS_SAATI": "19:05",
      "DONUS_SAATI": "",
      "SIRA": 9,
      "GIDIS_ENGELLI_DESTEGI": "True",
      "DONUS_ENGELLI_DESTEGI": "False",
      "BISIKLETLI_GIDIS": "True",
      "BISIKLETLI_DONUS": "False",
      "GIDIS_ELEKTRIKLI_OTOBUS": "False",
      "DONUS_ELEKTRIKLI_OTOBUS": "False"
    },
    {
      "_id": 86015,
      "HAT_NO": 816,
      "TARIFE_ID": 2,
      "GIDIS_SAATI": "06:00",
      "DONUS_SAATI": "06:40",
      "SIRA": 1,
      "GIDIS_ENGELLI_DESTEGI": "True",
      "DONUS_ENGELLI_DESTEGI": "True",
      "BISIKLETLI_GIDIS": "True",
      "BISIKLETLI_DONUS": "True",
      "GIDIS_ELEKTRIKLI_OTOBUS": "False",
      "DONUS_ELEKTRIKLI_OTOBUS": "False"
    },
    {
      "_id": 86016,
      "HAT_NO": 816,
      "TARIFE_ID": 2,
      "GIDIS_SAATI": "07:25",
      "DONUS_SAATI": "08:15",
      "SIRA": 2,
      "GIDIS_ENGELLI_DESTEGI": "True",
      "DONUS_ENGELLI_DESTEGI": "True",
      "BISIKLETLI_GIDIS": "True",
      "BISIKLETLI_DONUS": "True",
      "GIDIS_ELEKTRIKLI_OTOBUS": "False",
      "DONUS_ELEKTRIKLI_OTOBUS": "False"
    },
    {
      "_id": 86017,
      "HAT_NO": 816,
      "TARIFE_ID": 2,
      "GIDIS_SAATI": "09:05",
      "DONUS_SAATI": "10:05",
      "SIRA": 3,
      "GIDIS_ENGELLI_DESTEGI": "True",
      "DONUS_ENGELLI_DESTEGI": "True",
      "BISIKLETLI_GIDIS": "True",
      "BISIKLETLI_DONUS": "True",
      "GIDIS_ELEKTRIKLI_OTOBUS": "False",
      "DONUS_ELEKTRIKLI_OTOBUS": "False"
    },
    {
      "_id": 86018,
      "HAT_NO": 816,
      "TARIFE_ID": 2,
      "GIDIS_SAATI": "11:05",
      "DONUS_SAATI": "12:05",
      "SIRA": 4,
      "GIDIS_ENGELLI_DESTEGI": "True",
      "DONUS_ENGELLI_DESTEGI": "True",
      "BISIKLETLI_GIDIS": "True",
      "BISIKLETLI_DONUS": "True",
      "GIDIS_ELEKTRIKLI_OTOBUS": "False",
      "DONUS_ELEKTRIKLI_OTOBUS": "False"
    },
    {
      "_id": 86019,
      "HAT_NO": 816,
      "TARIFE_ID": 2,
      "GIDIS_SAATI": "13:05",
      "DONUS_SAATI": "14:05",
      "SIRA": 5,
      "GIDIS_ENGELLI_DESTEGI": "True",
      "DONUS_ENGELLI_DESTEGI": "True",
      "BISIKLETLI_GIDIS": "True",
      "BISIKLETLI_DONUS": "True",
      "GIDIS_ELEKTRIKLI_OTOBUS": "False",
      "DONUS_ELEKTRIKLI_OTOBUS": "False"
    },
    {
      "_id": 86020,
      "HAT_NO": 816,
      "TARIFE_ID": 2,
      "GIDIS_SAATI": "15:05",
      "DONUS_SAATI": "16:05",
      "SIRA": 6,
      "GIDIS_ENGELLI_DESTEGI": "True",
      "DONUS_ENGELLI_DESTEGI": "True",
      "BISIKLETLI_GIDIS": "True",
      "BISIKLETLI_DONUS": "True",
      "GIDIS_ELEKTRIKLI_OTOBUS": "False",
      "DONUS_ELEKTRIKLI_OTOBUS": "False"
    },
    {
      "_id": 86021,
      "HAT_NO": 816,
      "TARIFE_ID": 2,
      "GIDIS_SAATI": "17:05",
      "DONUS_SAATI": "18:05",
      "SIRA": 7,
      "GIDIS_ENGELLI_DESTEGI": "True",
      "DONUS_ENGELLI_DESTEGI": "True",
      "BISIKLETLI_GIDIS": "True",
      "BISIKLETLI_DONUS": "True",
      "GIDIS_ELEKTRIKLI_OTOBUS": "False",
      "DONUS_ELEKTRIKLI_OTOBUS": "False"
    },
    {
      "_id": 86022,
      "HAT_NO": 816,
      "TARIFE_ID": 2,
      "GIDIS_SAATI": "19:05",
      "DONUS_SAATI": "",
      "SIRA": 8,
      "GIDIS_ENGELLI_DESTEGI": "True",
      "DONUS_ENGELLI_DESTEGI": "False",
      "BISIKLETLI_GIDIS": "True",
      "BISIKLETLI_DONUS": "False",
      "GIDIS_ELEKTRIKLI_OTOBUS": "False",
      "DONUS_ELEKTRIKLI_OTOBUS": "False"
    },
    {
      "_id": 86023,
      "HAT_NO": 816,
      "TARIFE_ID": 1,
      "GIDIS_SAATI": "06:00",
      "DONUS_SAATI": "06:40",
      "SIRA": 1,
      "GIDIS_ENGELLI_DESTEGI": "True",
      "DONUS_ENGELLI_DESTEGI": "True",
      "BISIKLETLI_GIDIS": "True",
      "BISIKLETLI_DONUS": "True",
      "GIDIS_ELEKTRIKLI_OTOBUS": "False",
      "DONUS_ELEKTRIKLI_OTOBUS": "False"
    },
    {
      "_id": 86024,
      "HAT_NO": 816,
      "TARIFE_ID": 1,
      "GIDIS_SAATI": "06:45",
      "DONUS_SAATI": "08:15",
      "SIRA": 2,
      "GIDIS_ENGELLI_DESTEGI": "True",
      "DONUS_ENGELLI_DESTEGI": "True",
      "BISIKLETLI_GIDIS": "False",
      "BISIKLETLI_DONUS": "True",
      "GIDIS_ELEKTRIKLI_OTOBUS": "False",
      "DONUS_ELEKTRIKLI_OTOBUS": "False"
    },
    {
      "_id": 86025,
      "HAT_NO": 816,
      "TARIFE_ID": 1,
      "GIDIS_SAATI": "07:25",
      "DONUS_SAATI": "10:05",
      "SIRA": 3,
      "GIDIS_ENGELLI_DESTEGI": "True",
      "DONUS_ENGELLI_DESTEGI": "True",
      "BISIKLETLI_GIDIS": "True",
      "BISIKLETLI_DONUS": "True",
      "GIDIS_ELEKTRIKLI_OTOBUS": "False",
      "DONUS_ELEKTRIKLI_OTOBUS": "False"
    },
    {
      "_id": 86026,
      "HAT_NO": 816,
      "TARIFE_ID": 1,
      "GIDIS_SAATI": "09:05",
      "DONUS_SAATI": "12:05",
      "SIRA": 4,
      "GIDIS_ENGELLI_DESTEGI": "True",
      "DONUS_ENGELLI_DESTEGI": "True",
      "BISIKLETLI_GIDIS": "True",
      "BISIKLETLI_DONUS": "True",
      "GIDIS_ELEKTRIKLI_OTOBUS": "False",
      "DONUS_ELEKTRIKLI_OTOBUS": "False"
    },
    {
      "_id": 86027,
      "HAT_NO": 816,
      "TARIFE_ID": 1,
      "GIDIS_SAATI": "11:05",
      "DONUS_SAATI": "14:05",
      "SIRA": 5,
      "GIDIS_ENGELLI_DESTEGI": "True",
      "DONUS_ENGELLI_DESTEGI": "True",
      "BISIKLETLI_GIDIS": "True",
      "BISIKLETLI_DONUS": "True",
      "GIDIS_ELEKTRIKLI_OTOBUS": "False",
      "DONUS_ELEKTRIKLI_OTOBUS": "False"
    },
    {
      "_id": 86028,
      "HAT_NO": 816,
      "TARIFE_ID": 1,
      "GIDIS_SAATI": "13:05",
      "DONUS_SAATI": "16:05",
      "SIRA": 6,
      "GIDIS_ENGELLI_DESTEGI": "True",
      "DONUS_ENGELLI_DESTEGI": "True",
      "BISIKLETLI_GIDIS": "True",
      "BISIKLETLI_DONUS": "True",
      "GIDIS_ELEKTRIKLI_OTOBUS": "False",
      "DONUS_ELEKTRIKLI_OTOBUS": "False"
    },
    {
      "_id": 86029,
      "HAT_NO": 816,
      "TARIFE_ID": 1,
      "GIDIS_SAATI": "15:05",
      "DONUS_SAATI": "18:05",
      "SIRA": 7,
      "GIDIS_ENGELLI_DESTEGI": "True",
      "DONUS_ENGELLI_DESTEGI": "True",
      "BISIKLETLI_GIDIS": "True",
      "BISIKLETLI_DONUS": "True",
      "GIDIS_ELEKTRIKLI_OTOBUS": "False",
      "DONUS_ELEKTRIKLI_OTOBUS": "False"
    },
    {
      "_id": 86030,
      "HAT_NO": 816,
      "TARIFE_ID": 1,
      "GIDIS_SAATI": "17:05",
      "DONUS_SAATI": "",
      "SIRA": 8,
      "GIDIS_ENGELLI_DESTEGI": "True",
      "DONUS_ENGELLI_DESTEGI": "False",
      "BISIKLETLI_GIDIS": "True",
      "BISIKLETLI_DONUS": "False",
      "GIDIS_ELEKTRIKLI_OTOBUS": "False",
      "DONUS_ELEKTRIKLI_OTOBUS": "False"
    },
    {
      "_id": 86031,
      "HAT_NO": 816,
      "TARIFE_ID": 1,
      "GIDIS_SAATI": "19:05",
      "DONUS_SAATI": "",
      "SIRA": 9,
      "GIDIS_ENGELLI_DESTEGI": "True",
      "DONUS_ENGELLI_DESTEGI": "False",
      "BISIKLETLI_GIDIS": "True",
      "BISIKLETLI_DONUS": "False",
      "GIDIS_ELEKTRIKLI_OTOBUS": "False",
      "DONUS_ELEKTRIKLI_OTOBUS": "False"
    }
  ]
}
