{
  "updatedAt": "2026-04-12T14:06:18.944Z",
  "source": "izmir-open-data-js / ESHOT getHareketSaatleri",
  "hatNo": "877",
  "total": 84,
  "saatler": [
    {
      "_id": 93115,
      "HAT_NO": 877,
      "TARIFE_ID": 1,
      "GIDIS_SAATI": "06:10",
      "DONUS_SAATI": "07:10",
      "SIRA": 1,
      "GIDIS_ENGELLI_DESTEGI": "True",
      "DONUS_ENGELLI_DESTEGI": "True",
      "BISIKLETLI_GIDIS": "False",
      "BISIKLETLI_DONUS": "False",
      "GIDIS_ELEKTRIKLI_OTOBUS": "False",
      "DONUS_ELEKTRIKLI_OTOBUS": "False"
    },
    {
      "_id": 93116,
      "HAT_NO": 877,
      "TARIFE_ID": 1,
      "GIDIS_SAATI": "07:10",
      "DONUS_SAATI": "08:10",
      "SIRA": 2,
      "GIDIS_ENGELLI_DESTEGI": "True",
      "DONUS_ENGELLI_DESTEGI": "True",
      "BISIKLETLI_GIDIS": "True",
      "BISIKLETLI_DONUS": "True",
      "GIDIS_ELEKTRIKLI_OTOBUS": "False",
      "DONUS_ELEKTRIKLI_OTOBUS": "False"
    },
    {
      "_id": 93117,
      "HAT_NO": 877,
      "TARIFE_ID": 1,
      "GIDIS_SAATI": "08:10",
      "DONUS_SAATI": "10:10",
      "SIRA": 3,
      "GIDIS_ENGELLI_DESTEGI": "True",
      "DONUS_ENGELLI_DESTEGI": "True",
      "BISIKLETLI_GIDIS": "False",
      "BISIKLETLI_DONUS": "True",
      "GIDIS_ELEKTRIKLI_OTOBUS": "False",
      "DONUS_ELEKTRIKLI_OTOBUS": "False"
    },
    {
      "_id": 93118,
      "HAT_NO": 877,
      "TARIFE_ID": 1,
      "GIDIS_SAATI": "09:10",
      "DONUS_SAATI": "12:00",
      "SIRA": 4,
      "GIDIS_ENGELLI_DESTEGI": "True",
      "DONUS_ENGELLI_DESTEGI": "True",
      "BISIKLETLI_GIDIS": "True",
      "BISIKLETLI_DONUS": "True",
      "GIDIS_ELEKTRIKLI_OTOBUS": "False",
      "DONUS_ELEKTRIKLI_OTOBUS": "False"
    },
    {
      "_id": 93119,
      "HAT_NO": 877,
      "TARIFE_ID": 1,
      "GIDIS_SAATI": "11:00",
      "DONUS_SAATI": "14:00",
      "SIRA": 5,
      "GIDIS_ENGELLI_DESTEGI": "True",
      "DONUS_ENGELLI_DESTEGI": "True",
      "BISIKLETLI_GIDIS": "True",
      "BISIKLETLI_DONUS": "True",
      "GIDIS_ELEKTRIKLI_OTOBUS": "False",
      "DONUS_ELEKTRIKLI_OTOBUS": "False"
    },
    {
      "_id": 93120,
      "HAT_NO": 877,
      "TARIFE_ID": 1,
      "GIDIS_SAATI": "13:00",
      "DONUS_SAATI": "16:00",
      "SIRA": 6,
      "GIDIS_ENGELLI_DESTEGI": "True",
      "DONUS_ENGELLI_DESTEGI": "True",
      "BISIKLETLI_GIDIS": "True",
      "BISIKLETLI_DONUS": "True",
      "GIDIS_ELEKTRIKLI_OTOBUS": "False",
      "DONUS_ELEKTRIKLI_OTOBUS": "False"
    },
    {
      "_id": 93121,
      "HAT_NO": 877,
      "TARIFE_ID": 1,
      "GIDIS_SAATI": "15:00",
      "DONUS_SAATI": "17:00",
      "SIRA": 7,
      "GIDIS_ENGELLI_DESTEGI": "True",
      "DONUS_ENGELLI_DESTEGI": "True",
      "BISIKLETLI_GIDIS": "True",
      "BISIKLETLI_DONUS": "False",
      "GIDIS_ELEKTRIKLI_OTOBUS": "False",
      "DONUS_ELEKTRIKLI_OTOBUS": "False"
    },
    {
      "_id": 93122,
      "HAT_NO": 877,
      "TARIFE_ID": 1,
      "GIDIS_SAATI": "16:00",
      "DONUS_SAATI": "18:00",
      "SIRA": 8,
      "GIDIS_ENGELLI_DESTEGI": "True",
      "DONUS_ENGELLI_DESTEGI": "True",
      "BISIKLETLI_GIDIS": "False",
      "BISIKLETLI_DONUS": "True",
      "GIDIS_ELEKTRIKLI_OTOBUS": "False",
      "DONUS_ELEKTRIKLI_OTOBUS": "False"
    },
    {
      "_id": 93123,
      "HAT_NO": 877,
      "TARIFE_ID": 1,
      "GIDIS_SAATI": "17:00",
      "DONUS_SAATI": "19:00",
      "SIRA": 9,
      "GIDIS_ENGELLI_DESTEGI": "True",
      "DONUS_ENGELLI_DESTEGI": "True",
      "BISIKLETLI_GIDIS": "True",
      "BISIKLETLI_DONUS": "False",
      "GIDIS_ELEKTRIKLI_OTOBUS": "False",
      "DONUS_ELEKTRIKLI_OTOBUS": "False"
    },
    {
      "_id": 93124,
      "HAT_NO": 877,
      "TARIFE_ID": 1,
      "GIDIS_SAATI": "18:00",
      "DONUS_SAATI": "20:00",
      "SIRA": 10,
      "GIDIS_ENGELLI_DESTEGI": "True",
      "DONUS_ENGELLI_DESTEGI": "True",
      "BISIKLETLI_GIDIS": "False",
      "BISIKLETLI_DONUS": "True",
      "GIDIS_ELEKTRIKLI_OTOBUS": "False",
      "DONUS_ELEKTRIKLI_OTOBUS": "False"
    },
    {
      "_id": 93125,
      "HAT_NO": 877,
      "TARIFE_ID": 1,
      "GIDIS_SAATI": "19:00",
      "DONUS_SAATI": "",
      "SIRA": 11,
      "GIDIS_ENGELLI_DESTEGI": "True",
      "DONUS_ENGELLI_DESTEGI": "False",
      "BISIKLETLI_GIDIS": "True",
      "BISIKLETLI_DONUS": "False",
      "GIDIS_ELEKTRIKLI_OTOBUS": "False",
      "DONUS_ELEKTRIKLI_OTOBUS": "False"
    },
    {
      "_id": 93126,
      "HAT_NO": 877,
      "TARIFE_ID": 1,
      "GIDIS_SAATI": "06:10",
      "DONUS_SAATI": "07:10",
      "SIRA": 1,
      "GIDIS_ENGELLI_DESTEGI": "True",
      "DONUS_ENGELLI_DESTEGI": "True",
      "BISIKLETLI_GIDIS": "False",
      "BISIKLETLI_DONUS": "False",
      "GIDIS_ELEKTRIKLI_OTOBUS": "False",
      "DONUS_ELEKTRIKLI_OTOBUS": "False"
    },
    {
      "_id": 93127,
      "HAT_NO": 877,
      "TARIFE_ID": 1,
      "GIDIS_SAATI": "07:10",
      "DONUS_SAATI": "08:10",
      "SIRA": 2,
      "GIDIS_ENGELLI_DESTEGI": "True",
      "DONUS_ENGELLI_DESTEGI": "True",
      "BISIKLETLI_GIDIS": "True",
      "BISIKLETLI_DONUS": "True",
      "GIDIS_ELEKTRIKLI_OTOBUS": "False",
      "DONUS_ELEKTRIKLI_OTOBUS": "False"
    },
    {
      "_id": 93128,
      "HAT_NO": 877,
      "TARIFE_ID": 1,
      "GIDIS_SAATI": "08:10",
      "DONUS_SAATI": "10:10",
      "SIRA": 3,
      "GIDIS_ENGELLI_DESTEGI": "True",
      "DONUS_ENGELLI_DESTEGI": "True",
      "BISIKLETLI_GIDIS": "False",
      "BISIKLETLI_DONUS": "True",
      "GIDIS_ELEKTRIKLI_OTOBUS": "False",
      "DONUS_ELEKTRIKLI_OTOBUS": "False"
    },
    {
      "_id": 93129,
      "HAT_NO": 877,
      "TARIFE_ID": 1,
      "GIDIS_SAATI": "09:10",
      "DONUS_SAATI": "12:00",
      "SIRA": 4,
      "GIDIS_ENGELLI_DESTEGI": "True",
      "DONUS_ENGELLI_DESTEGI": "True",
      "BISIKLETLI_GIDIS": "True",
      "BISIKLETLI_DONUS": "True",
      "GIDIS_ELEKTRIKLI_OTOBUS": "False",
      "DONUS_ELEKTRIKLI_OTOBUS": "False"
    },
    {
      "_id": 93130,
      "HAT_NO": 877,
      "TARIFE_ID": 1,
      "GIDIS_SAATI": "11:00",
      "DONUS_SAATI": "14:00",
      "SIRA": 5,
      "GIDIS_ENGELLI_DESTEGI": "True",
      "DONUS_ENGELLI_DESTEGI": "True",
      "BISIKLETLI_GIDIS": "True",
      "BISIKLETLI_DONUS": "True",
      "GIDIS_ELEKTRIKLI_OTOBUS": "False",
      "DONUS_ELEKTRIKLI_OTOBUS": "False"
    },
    {
      "_id": 93131,
      "HAT_NO": 877,
      "TARIFE_ID": 1,
      "GIDIS_SAATI": "13:00",
      "DONUS_SAATI": "16:00",
      "SIRA": 6,
      "GIDIS_ENGELLI_DESTEGI": "True",
      "DONUS_ENGELLI_DESTEGI": "True",
      "BISIKLETLI_GIDIS": "True",
      "BISIKLETLI_DONUS": "True",
      "GIDIS_ELEKTRIKLI_OTOBUS": "False",
      "DONUS_ELEKTRIKLI_OTOBUS": "False"
    },
    {
      "_id": 93132,
      "HAT_NO": 877,
      "TARIFE_ID": 1,
      "GIDIS_SAATI": "15:00",
      "DONUS_SAATI": "17:00",
      "SIRA": 7,
      "GIDIS_ENGELLI_DESTEGI": "True",
      "DONUS_ENGELLI_DESTEGI": "True",
      "BISIKLETLI_GIDIS": "True",
      "BISIKLETLI_DONUS": "False",
      "GIDIS_ELEKTRIKLI_OTOBUS": "False",
      "DONUS_ELEKTRIKLI_OTOBUS": "False"
    },
    {
      "_id": 93133,
      "HAT_NO": 877,
      "TARIFE_ID": 1,
      "GIDIS_SAATI": "16:00",
      "DONUS_SAATI": "18:00",
      "SIRA": 8,
      "GIDIS_ENGELLI_DESTEGI": "True",
      "DONUS_ENGELLI_DESTEGI": "True",
      "BISIKLETLI_GIDIS": "False",
      "BISIKLETLI_DONUS": "True",
      "GIDIS_ELEKTRIKLI_OTOBUS": "False",
      "DONUS_ELEKTRIKLI_OTOBUS": "False"
    },
    {
      "_id": 93134,
      "HAT_NO": 877,
      "TARIFE_ID": 1,
      "GIDIS_SAATI": "17:00",
      "DONUS_SAATI": "19:00",
      "SIRA": 9,
      "GIDIS_ENGELLI_DESTEGI": "True",
      "DONUS_ENGELLI_DESTEGI": "True",
      "BISIKLETLI_GIDIS": "True",
      "BISIKLETLI_DONUS": "False",
      "GIDIS_ELEKTRIKLI_OTOBUS": "False",
      "DONUS_ELEKTRIKLI_OTOBUS": "False"
    },
    {
      "_id": 93135,
      "HAT_NO": 877,
      "TARIFE_ID": 1,
      "GIDIS_SAATI": "18:00",
      "DONUS_SAATI": "20:00",
      "SIRA": 10,
      "GIDIS_ENGELLI_DESTEGI": "True",
      "DONUS_ENGELLI_DESTEGI": "True",
      "BISIKLETLI_GIDIS": "False",
      "BISIKLETLI_DONUS": "True",
      "GIDIS_ELEKTRIKLI_OTOBUS": "False",
      "DONUS_ELEKTRIKLI_OTOBUS": "False"
    },
    {
      "_id": 93136,
      "HAT_NO": 877,
      "TARIFE_ID": 1,
      "GIDIS_SAATI": "19:00",
      "DONUS_SAATI": "",
      "SIRA": 11,
      "GIDIS_ENGELLI_DESTEGI": "True",
      "DONUS_ENGELLI_DESTEGI": "False",
      "BISIKLETLI_GIDIS": "True",
      "BISIKLETLI_DONUS": "False",
      "GIDIS_ELEKTRIKLI_OTOBUS": "False",
      "DONUS_ELEKTRIKLI_OTOBUS": "False"
    },
    {
      "_id": 93137,
      "HAT_NO": 877,
      "TARIFE_ID": 1,
      "GIDIS_SAATI": "06:10",
      "DONUS_SAATI": "07:10",
      "SIRA": 1,
      "GIDIS_ENGELLI_DESTEGI": "True",
      "DONUS_ENGELLI_DESTEGI": "True",
      "BISIKLETLI_GIDIS": "False",
      "BISIKLETLI_DONUS": "False",
      "GIDIS_ELEKTRIKLI_OTOBUS": "False",
      "DONUS_ELEKTRIKLI_OTOBUS": "False"
    },
    {
      "_id": 93138,
      "HAT_NO": 877,
      "TARIFE_ID": 1,
      "GIDIS_SAATI": "07:10",
      "DONUS_SAATI": "08:10",
      "SIRA": 2,
      "GIDIS_ENGELLI_DESTEGI": "True",
      "DONUS_ENGELLI_DESTEGI": "True",
      "BISIKLETLI_GIDIS": "True",
      "BISIKLETLI_DONUS": "True",
      "GIDIS_ELEKTRIKLI_OTOBUS": "False",
      "DONUS_ELEKTRIKLI_OTOBUS": "False"
    },
    {
      "_id": 93139,
      "HAT_NO": 877,
      "TARIFE_ID": 1,
      "GIDIS_SAATI": "08:10",
      "DONUS_SAATI": "10:10",
      "SIRA": 3,
      "GIDIS_ENGELLI_DESTEGI": "True",
      "DONUS_ENGELLI_DESTEGI": "True",
      "BISIKLETLI_GIDIS": "False",
      "BISIKLETLI_DONUS": "True",
      "GIDIS_ELEKTRIKLI_OTOBUS": "False",
      "DONUS_ELEKTRIKLI_OTOBUS": "False"
    },
    {
      "_id": 93140,
      "HAT_NO": 877,
      "TARIFE_ID": 1,
      "GIDIS_SAATI": "09:10",
      "DONUS_SAATI": "12:00",
      "SIRA": 4,
      "GIDIS_ENGELLI_DESTEGI": "True",
      "DONUS_ENGELLI_DESTEGI": "True",
      "BISIKLETLI_GIDIS": "True",
      "BISIKLETLI_DONUS": "True",
      "GIDIS_ELEKTRIKLI_OTOBUS": "False",
      "DONUS_ELEKTRIKLI_OTOBUS": "False"
    },
    {
      "_id": 93141,
      "HAT_NO": 877,
      "TARIFE_ID": 1,
      "GIDIS_SAATI": "11:00",
      "DONUS_SAATI": "14:00",
      "SIRA": 5,
      "GIDIS_ENGELLI_DESTEGI": "True",
      "DONUS_ENGELLI_DESTEGI": "True",
      "BISIKLETLI_GIDIS": "True",
      "BISIKLETLI_DONUS": "True",
      "GIDIS_ELEKTRIKLI_OTOBUS": "False",
      "DONUS_ELEKTRIKLI_OTOBUS": "False"
    },
    {
      "_id": 93142,
      "HAT_NO": 877,
      "TARIFE_ID": 1,
      "GIDIS_SAATI": "13:00",
      "DONUS_SAATI": "16:00",
      "SIRA": 6,
      "GIDIS_ENGELLI_DESTEGI": "True",
      "DONUS_ENGELLI_DESTEGI": "True",
      "BISIKLETLI_GIDIS": "True",
      "BISIKLETLI_DONUS": "True",
      "GIDIS_ELEKTRIKLI_OTOBUS": "False",
      "DONUS_ELEKTRIKLI_OTOBUS": "False"
    },
    {
      "_id": 93143,
      "HAT_NO": 877,
      "TARIFE_ID": 1,
      "GIDIS_SAATI": "15:00",
      "DONUS_SAATI": "17:00",
      "SIRA": 7,
      "GIDIS_ENGELLI_DESTEGI": "True",
      "DONUS_ENGELLI_DESTEGI": "True",
      "BISIKLETLI_GIDIS": "True",
      "BISIKLETLI_DONUS": "False",
      "GIDIS_ELEKTRIKLI_OTOBUS": "False",
      "DONUS_ELEKTRIKLI_OTOBUS": "False"
    },
    {
      "_id": 93144,
      "HAT_NO": 877,
      "TARIFE_ID": 1,
      "GIDIS_SAATI": "16:00",
      "DONUS_SAATI": "18:00",
      "SIRA": 8,
      "GIDIS_ENGELLI_DESTEGI": "True",
      "DONUS_ENGELLI_DESTEGI": "True",
      "BISIKLETLI_GIDIS": "False",
      "BISIKLETLI_DONUS": "True",
      "GIDIS_ELEKTRIKLI_OTOBUS": "False",
      "DONUS_ELEKTRIKLI_OTOBUS": "False"
    },
    {
      "_id": 93145,
      "HAT_NO": 877,
      "TARIFE_ID": 1,
      "GIDIS_SAATI": "17:00",
      "DONUS_SAATI": "19:00",
      "SIRA": 9,
      "GIDIS_ENGELLI_DESTEGI": "True",
      "DONUS_ENGELLI_DESTEGI": "True",
      "BISIKLETLI_GIDIS": "True",
      "BISIKLETLI_DONUS": "False",
      "GIDIS_ELEKTRIKLI_OTOBUS": "False",
      "DONUS_ELEKTRIKLI_OTOBUS": "False"
    },
    {
      "_id": 93146,
      "HAT_NO": 877,
      "TARIFE_ID": 1,
      "GIDIS_SAATI": "18:00",
      "DONUS_SAATI": "20:00",
      "SIRA": 10,
      "GIDIS_ENGELLI_DESTEGI": "True",
      "DONUS_ENGELLI_DESTEGI": "True",
      "BISIKLETLI_GIDIS": "False",
      "BISIKLETLI_DONUS": "True",
      "GIDIS_ELEKTRIKLI_OTOBUS": "False",
      "DONUS_ELEKTRIKLI_OTOBUS": "False"
    },
    {
      "_id": 93147,
      "HAT_NO": 877,
      "TARIFE_ID": 1,
      "GIDIS_SAATI": "19:00",
      "DONUS_SAATI": "",
      "SIRA": 11,
      "GIDIS_ENGELLI_DESTEGI": "True",
      "DONUS_ENGELLI_DESTEGI": "False",
      "BISIKLETLI_GIDIS": "True",
      "BISIKLETLI_DONUS": "False",
      "GIDIS_ELEKTRIKLI_OTOBUS": "False",
      "DONUS_ELEKTRIKLI_OTOBUS": "False"
    },
    {
      "_id": 93148,
      "HAT_NO": 877,
      "TARIFE_ID": 1,
      "GIDIS_SAATI": "06:10",
      "DONUS_SAATI": "07:10",
      "SIRA": 1,
      "GIDIS_ENGELLI_DESTEGI": "True",
      "DONUS_ENGELLI_DESTEGI": "True",
      "BISIKLETLI_GIDIS": "False",
      "BISIKLETLI_DONUS": "False",
      "GIDIS_ELEKTRIKLI_OTOBUS": "False",
      "DONUS_ELEKTRIKLI_OTOBUS": "False"
    },
    {
      "_id": 93149,
      "HAT_NO": 877,
      "TARIFE_ID": 1,
      "GIDIS_SAATI": "07:10",
      "DONUS_SAATI": "08:10",
      "SIRA": 2,
      "GIDIS_ENGELLI_DESTEGI": "True",
      "DONUS_ENGELLI_DESTEGI": "True",
      "BISIKLETLI_GIDIS": "True",
      "BISIKLETLI_DONUS": "True",
      "GIDIS_ELEKTRIKLI_OTOBUS": "False",
      "DONUS_ELEKTRIKLI_OTOBUS": "False"
    },
    {
      "_id": 93150,
      "HAT_NO": 877,
      "TARIFE_ID": 1,
      "GIDIS_SAATI": "08:10",
      "DONUS_SAATI": "10:10",
      "SIRA": 3,
      "GIDIS_ENGELLI_DESTEGI": "True",
      "DONUS_ENGELLI_DESTEGI": "True",
      "BISIKLETLI_GIDIS": "False",
      "BISIKLETLI_DONUS": "True",
      "GIDIS_ELEKTRIKLI_OTOBUS": "False",
      "DONUS_ELEKTRIKLI_OTOBUS": "False"
    },
    {
      "_id": 93151,
      "HAT_NO": 877,
      "TARIFE_ID": 1,
      "GIDIS_SAATI": "09:10",
      "DONUS_SAATI": "12:00",
      "SIRA": 4,
      "GIDIS_ENGELLI_DESTEGI": "True",
      "DONUS_ENGELLI_DESTEGI": "True",
      "BISIKLETLI_GIDIS": "True",
      "BISIKLETLI_DONUS": "True",
      "GIDIS_ELEKTRIKLI_OTOBUS": "False",
      "DONUS_ELEKTRIKLI_OTOBUS": "False"
    },
    {
      "_id": 93152,
      "HAT_NO": 877,
      "TARIFE_ID": 1,
      "GIDIS_SAATI": "11:00",
      "DONUS_SAATI": "14:00",
      "SIRA": 5,
      "GIDIS_ENGELLI_DESTEGI": "True",
      "DONUS_ENGELLI_DESTEGI": "True",
      "BISIKLETLI_GIDIS": "True",
      "BISIKLETLI_DONUS": "True",
      "GIDIS_ELEKTRIKLI_OTOBUS": "False",
      "DONUS_ELEKTRIKLI_OTOBUS": "False"
    },
    {
      "_id": 93153,
      "HAT_NO": 877,
      "TARIFE_ID": 1,
      "GIDIS_SAATI": "13:00",
      "DONUS_SAATI": "16:00",
      "SIRA": 6,
      "GIDIS_ENGELLI_DESTEGI": "True",
      "DONUS_ENGELLI_DESTEGI": "True",
      "BISIKLETLI_GIDIS": "True",
      "BISIKLETLI_DONUS": "True",
      "GIDIS_ELEKTRIKLI_OTOBUS": "False",
      "DONUS_ELEKTRIKLI_OTOBUS": "False"
    },
    {
      "_id": 93154,
      "HAT_NO": 877,
      "TARIFE_ID": 1,
      "GIDIS_SAATI": "15:00",
      "DONUS_SAATI": "17:00",
      "SIRA": 7,
      "GIDIS_ENGELLI_DESTEGI": "True",
      "DONUS_ENGELLI_DESTEGI": "True",
      "BISIKLETLI_GIDIS": "True",
      "BISIKLETLI_DONUS": "False",
      "GIDIS_ELEKTRIKLI_OTOBUS": "False",
      "DONUS_ELEKTRIKLI_OTOBUS": "False"
    },
    {
      "_id": 93155,
      "HAT_NO": 877,
      "TARIFE_ID": 1,
      "GIDIS_SAATI": "16:00",
      "DONUS_SAATI": "18:00",
      "SIRA": 8,
      "GIDIS_ENGELLI_DESTEGI": "True",
      "DONUS_ENGELLI_DESTEGI": "True",
      "BISIKLETLI_GIDIS": "False",
      "BISIKLETLI_DONUS": "True",
      "GIDIS_ELEKTRIKLI_OTOBUS": "False",
      "DONUS_ELEKTRIKLI_OTOBUS": "False"
    },
    {
      "_id": 93156,
      "HAT_NO": 877,
      "TARIFE_ID": 1,
      "GIDIS_SAATI": "17:00",
      "DONUS_SAATI": "19:00",
      "SIRA": 9,
      "GIDIS_ENGELLI_DESTEGI": "True",
      "DONUS_ENGELLI_DESTEGI": "True",
      "BISIKLETLI_GIDIS": "True",
      "BISIKLETLI_DONUS": "False",
      "GIDIS_ELEKTRIKLI_OTOBUS": "False",
      "DONUS_ELEKTRIKLI_OTOBUS": "False"
    },
    {
      "_id": 93157,
      "HAT_NO": 877,
      "TARIFE_ID": 1,
      "GIDIS_SAATI": "18:00",
      "DONUS_SAATI": "20:00",
      "SIRA": 10,
      "GIDIS_ENGELLI_DESTEGI": "True",
      "DONUS_ENGELLI_DESTEGI": "True",
      "BISIKLETLI_GIDIS": "False",
      "BISIKLETLI_DONUS": "True",
      "GIDIS_ELEKTRIKLI_OTOBUS": "False",
      "DONUS_ELEKTRIKLI_OTOBUS": "False"
    },
    {
      "_id": 93158,
      "HAT_NO": 877,
      "TARIFE_ID": 1,
      "GIDIS_SAATI": "19:00",
      "DONUS_SAATI": "",
      "SIRA": 11,
      "GIDIS_ENGELLI_DESTEGI": "True",
      "DONUS_ENGELLI_DESTEGI": "False",
      "BISIKLETLI_GIDIS": "True",
      "BISIKLETLI_DONUS": "False",
      "GIDIS_ELEKTRIKLI_OTOBUS": "False",
      "DONUS_ELEKTRIKLI_OTOBUS": "False"
    },
    {
      "_id": 93159,
      "HAT_NO": 877,
      "TARIFE_ID": 1,
      "GIDIS_SAATI": "06:10",
      "DONUS_SAATI": "07:10",
      "SIRA": 1,
      "GIDIS_ENGELLI_DESTEGI": "True",
      "DONUS_ENGELLI_DESTEGI": "True",
      "BISIKLETLI_GIDIS": "False",
      "BISIKLETLI_DONUS": "False",
      "GIDIS_ELEKTRIKLI_OTOBUS": "False",
      "DONUS_ELEKTRIKLI_OTOBUS": "False"
    },
    {
      "_id": 93160,
      "HAT_NO": 877,
      "TARIFE_ID": 1,
      "GIDIS_SAATI": "07:10",
      "DONUS_SAATI": "08:10",
      "SIRA": 2,
      "GIDIS_ENGELLI_DESTEGI": "True",
      "DONUS_ENGELLI_DESTEGI": "True",
      "BISIKLETLI_GIDIS": "True",
      "BISIKLETLI_DONUS": "True",
      "GIDIS_ELEKTRIKLI_OTOBUS": "False",
      "DONUS_ELEKTRIKLI_OTOBUS": "False"
    },
    {
      "_id": 93161,
      "HAT_NO": 877,
      "TARIFE_ID": 1,
      "GIDIS_SAATI": "08:10",
      "DONUS_SAATI": "10:10",
      "SIRA": 3,
      "GIDIS_ENGELLI_DESTEGI": "True",
      "DONUS_ENGELLI_DESTEGI": "True",
      "BISIKLETLI_GIDIS": "False",
      "BISIKLETLI_DONUS": "True",
      "GIDIS_ELEKTRIKLI_OTOBUS": "False",
      "DONUS_ELEKTRIKLI_OTOBUS": "False"
    },
    {
      "_id": 93162,
      "HAT_NO": 877,
      "TARIFE_ID": 1,
      "GIDIS_SAATI": "09:10",
      "DONUS_SAATI": "12:00",
      "SIRA": 4,
      "GIDIS_ENGELLI_DESTEGI": "True",
      "DONUS_ENGELLI_DESTEGI": "True",
      "BISIKLETLI_GIDIS": "True",
      "BISIKLETLI_DONUS": "True",
      "GIDIS_ELEKTRIKLI_OTOBUS": "False",
      "DONUS_ELEKTRIKLI_OTOBUS": "False"
    },
    {
      "_id": 93163,
      "HAT_NO": 877,
      "TARIFE_ID": 1,
      "GIDIS_SAATI": "11:00",
      "DONUS_SAATI": "14:00",
      "SIRA": 5,
      "GIDIS_ENGELLI_DESTEGI": "True",
      "DONUS_ENGELLI_DESTEGI": "True",
      "BISIKLETLI_GIDIS": "True",
      "BISIKLETLI_DONUS": "True",
      "GIDIS_ELEKTRIKLI_OTOBUS": "False",
      "DONUS_ELEKTRIKLI_OTOBUS": "False"
    },
    {
      "_id": 93164,
      "HAT_NO": 877,
      "TARIFE_ID": 1,
      "GIDIS_SAATI": "13:00",
      "DONUS_SAATI": "16:00",
      "SIRA": 6,
      "GIDIS_ENGELLI_DESTEGI": "True",
      "DONUS_ENGELLI_DESTEGI": "True",
      "BISIKLETLI_GIDIS": "True",
      "BISIKLETLI_DONUS": "True",
      "GIDIS_ELEKTRIKLI_OTOBUS": "False",
      "DONUS_ELEKTRIKLI_OTOBUS": "False"
    },
    {
      "_id": 93165,
      "HAT_NO": 877,
      "TARIFE_ID": 1,
      "GIDIS_SAATI": "15:00",
      "DONUS_SAATI": "17:00",
      "SIRA": 7,
      "GIDIS_ENGELLI_DESTEGI": "True",
      "DONUS_ENGELLI_DESTEGI": "True",
      "BISIKLETLI_GIDIS": "True",
      "BISIKLETLI_DONUS": "False",
      "GIDIS_ELEKTRIKLI_OTOBUS": "False",
      "DONUS_ELEKTRIKLI_OTOBUS": "False"
    },
    {
      "_id": 93166,
      "HAT_NO": 877,
      "TARIFE_ID": 1,
      "GIDIS_SAATI": "16:00",
      "DONUS_SAATI": "18:00",
      "SIRA": 8,
      "GIDIS_ENGELLI_DESTEGI": "True",
      "DONUS_ENGELLI_DESTEGI": "True",
      "BISIKLETLI_GIDIS": "False",
      "BISIKLETLI_DONUS": "True",
      "GIDIS_ELEKTRIKLI_OTOBUS": "False",
      "DONUS_ELEKTRIKLI_OTOBUS": "False"
    },
    {
      "_id": 93167,
      "HAT_NO": 877,
      "TARIFE_ID": 1,
      "GIDIS_SAATI": "17:00",
      "DONUS_SAATI": "19:00",
      "SIRA": 9,
      "GIDIS_ENGELLI_DESTEGI": "True",
      "DONUS_ENGELLI_DESTEGI": "True",
      "BISIKLETLI_GIDIS": "True",
      "BISIKLETLI_DONUS": "False",
      "GIDIS_ELEKTRIKLI_OTOBUS": "False",
      "DONUS_ELEKTRIKLI_OTOBUS": "False"
    },
    {
      "_id": 93168,
      "HAT_NO": 877,
      "TARIFE_ID": 1,
      "GIDIS_SAATI": "18:00",
      "DONUS_SAATI": "20:00",
      "SIRA": 10,
      "GIDIS_ENGELLI_DESTEGI": "True",
      "DONUS_ENGELLI_DESTEGI": "True",
      "BISIKLETLI_GIDIS": "False",
      "BISIKLETLI_DONUS": "True",
      "GIDIS_ELEKTRIKLI_OTOBUS": "False",
      "DONUS_ELEKTRIKLI_OTOBUS": "False"
    },
    {
      "_id": 93169,
      "HAT_NO": 877,
      "TARIFE_ID": 1,
      "GIDIS_SAATI": "19:00",
      "DONUS_SAATI": "",
      "SIRA": 11,
      "GIDIS_ENGELLI_DESTEGI": "True",
      "DONUS_ENGELLI_DESTEGI": "False",
      "BISIKLETLI_GIDIS": "True",
      "BISIKLETLI_DONUS": "False",
      "GIDIS_ELEKTRIKLI_OTOBUS": "False",
      "DONUS_ELEKTRIKLI_OTOBUS": "False"
    },
    {
      "_id": 93170,
      "HAT_NO": 877,
      "TARIFE_ID": 2,
      "GIDIS_SAATI": "06:10",
      "DONUS_SAATI": "07:10",
      "SIRA": 1,
      "GIDIS_ENGELLI_DESTEGI": "True",
      "DONUS_ENGELLI_DESTEGI": "True",
      "BISIKLETLI_GIDIS": "False",
      "BISIKLETLI_DONUS": "False",
      "GIDIS_ELEKTRIKLI_OTOBUS": "False",
      "DONUS_ELEKTRIKLI_OTOBUS": "False"
    },
    {
      "_id": 93171,
      "HAT_NO": 877,
      "TARIFE_ID": 2,
      "GIDIS_SAATI": "07:10",
      "DONUS_SAATI": "08:10",
      "SIRA": 2,
      "GIDIS_ENGELLI_DESTEGI": "True",
      "DONUS_ENGELLI_DESTEGI": "True",
      "BISIKLETLI_GIDIS": "True",
      "BISIKLETLI_DONUS": "True",
      "GIDIS_ELEKTRIKLI_OTOBUS": "False",
      "DONUS_ELEKTRIKLI_OTOBUS": "False"
    },
    {
      "_id": 93172,
      "HAT_NO": 877,
      "TARIFE_ID": 2,
      "GIDIS_SAATI": "08:10",
      "DONUS_SAATI": "10:10",
      "SIRA": 3,
      "GIDIS_ENGELLI_DESTEGI": "True",
      "DONUS_ENGELLI_DESTEGI": "True",
      "BISIKLETLI_GIDIS": "False",
      "BISIKLETLI_DONUS": "True",
      "GIDIS_ELEKTRIKLI_OTOBUS": "False",
      "DONUS_ELEKTRIKLI_OTOBUS": "False"
    },
    {
      "_id": 93173,
      "HAT_NO": 877,
      "TARIFE_ID": 2,
      "GIDIS_SAATI": "09:10",
      "DONUS_SAATI": "12:00",
      "SIRA": 4,
      "GIDIS_ENGELLI_DESTEGI": "True",
      "DONUS_ENGELLI_DESTEGI": "True",
      "BISIKLETLI_GIDIS": "True",
      "BISIKLETLI_DONUS": "True",
      "GIDIS_ELEKTRIKLI_OTOBUS": "False",
      "DONUS_ELEKTRIKLI_OTOBUS": "False"
    },
    {
      "_id": 93174,
      "HAT_NO": 877,
      "TARIFE_ID": 2,
      "GIDIS_SAATI": "11:00",
      "DONUS_SAATI": "14:00",
      "SIRA": 5,
      "GIDIS_ENGELLI_DESTEGI": "True",
      "DONUS_ENGELLI_DESTEGI": "True",
      "BISIKLETLI_GIDIS": "True",
      "BISIKLETLI_DONUS": "True",
      "GIDIS_ELEKTRIKLI_OTOBUS": "False",
      "DONUS_ELEKTRIKLI_OTOBUS": "False"
    },
    {
      "_id": 93175,
      "HAT_NO": 877,
      "TARIFE_ID": 2,
      "GIDIS_SAATI": "13:00",
      "DONUS_SAATI": "16:00",
      "SIRA": 6,
      "GIDIS_ENGELLI_DESTEGI": "True",
      "DONUS_ENGELLI_DESTEGI": "True",
      "BISIKLETLI_GIDIS": "True",
      "BISIKLETLI_DONUS": "True",
      "GIDIS_ELEKTRIKLI_OTOBUS": "False",
      "DONUS_ELEKTRIKLI_OTOBUS": "False"
    },
    {
      "_id": 93176,
      "HAT_NO": 877,
      "TARIFE_ID": 2,
      "GIDIS_SAATI": "15:00",
      "DONUS_SAATI": "17:00",
      "SIRA": 7,
      "GIDIS_ENGELLI_DESTEGI": "True",
      "DONUS_ENGELLI_DESTEGI": "True",
      "BISIKLETLI_GIDIS": "True",
      "BISIKLETLI_DONUS": "False",
      "GIDIS_ELEKTRIKLI_OTOBUS": "False",
      "DONUS_ELEKTRIKLI_OTOBUS": "False"
    },
    {
      "_id": 93177,
      "HAT_NO": 877,
      "TARIFE_ID": 2,
      "GIDIS_SAATI": "16:00",
      "DONUS_SAATI": "18:00",
      "SIRA": 8,
      "GIDIS_ENGELLI_DESTEGI": "True",
      "DONUS_ENGELLI_DESTEGI": "True",
      "BISIKLETLI_GIDIS": "False",
      "BISIKLETLI_DONUS": "True",
      "GIDIS_ELEKTRIKLI_OTOBUS": "False",
      "DONUS_ELEKTRIKLI_OTOBUS": "False"
    },
    {
      "_id": 93178,
      "HAT_NO": 877,
      "TARIFE_ID": 2,
      "GIDIS_SAATI": "17:00",
      "DONUS_SAATI": "19:00",
      "SIRA": 9,
      "GIDIS_ENGELLI_DESTEGI": "True",
      "DONUS_ENGELLI_DESTEGI": "True",
      "BISIKLETLI_GIDIS": "True",
      "BISIKLETLI_DONUS": "False",
      "GIDIS_ELEKTRIKLI_OTOBUS": "False",
      "DONUS_ELEKTRIKLI_OTOBUS": "False"
    },
    {
      "_id": 93179,
      "HAT_NO": 877,
      "TARIFE_ID": 2,
      "GIDIS_SAATI": "18:00",
      "DONUS_SAATI": "20:00",
      "SIRA": 10,
      "GIDIS_ENGELLI_DESTEGI": "True",
      "DONUS_ENGELLI_DESTEGI": "True",
      "BISIKLETLI_GIDIS": "False",
      "BISIKLETLI_DONUS": "True",
      "GIDIS_ELEKTRIKLI_OTOBUS": "False",
      "DONUS_ELEKTRIKLI_OTOBUS": "False"
    },
    {
      "_id": 93180,
      "HAT_NO": 877,
      "TARIFE_ID": 2,
      "GIDIS_SAATI": "19:00",
      "DONUS_SAATI": "",
      "SIRA": 11,
      "GIDIS_ENGELLI_DESTEGI": "True",
      "DONUS_ENGELLI_DESTEGI": "False",
      "BISIKLETLI_GIDIS": "True",
      "BISIKLETLI_DONUS": "False",
      "GIDIS_ELEKTRIKLI_OTOBUS": "False",
      "DONUS_ELEKTRIKLI_OTOBUS": "False"
    },
    {
      "_id": 93181,
      "HAT_NO": 877,
      "TARIFE_ID": 3,
      "GIDIS_SAATI": "06:10",
      "DONUS_SAATI": "07:10",
      "SIRA": 1,
      "GIDIS_ENGELLI_DESTEGI": "True",
      "DONUS_ENGELLI_DESTEGI": "True",
      "BISIKLETLI_GIDIS": "True",
      "BISIKLETLI_DONUS": "True",
      "GIDIS_ELEKTRIKLI_OTOBUS": "False",
      "DONUS_ELEKTRIKLI_OTOBUS": "False"
    },
    {
      "_id": 93182,
      "HAT_NO": 877,
      "TARIFE_ID": 3,
      "GIDIS_SAATI": "08:10",
      "DONUS_SAATI": "09:10",
      "SIRA": 2,
      "GIDIS_ENGELLI_DESTEGI": "True",
      "DONUS_ENGELLI_DESTEGI": "True",
      "BISIKLETLI_GIDIS": "True",
      "BISIKLETLI_DONUS": "True",
      "GIDIS_ELEKTRIKLI_OTOBUS": "False",
      "DONUS_ELEKTRIKLI_OTOBUS": "False"
    },
    {
      "_id": 93183,
      "HAT_NO": 877,
      "TARIFE_ID": 3,
      "GIDIS_SAATI": "10:10",
      "DONUS_SAATI": "11:10",
      "SIRA": 3,
      "GIDIS_ENGELLI_DESTEGI": "True",
      "DONUS_ENGELLI_DESTEGI": "True",
      "BISIKLETLI_GIDIS": "True",
      "BISIKLETLI_DONUS": "True",
      "GIDIS_ELEKTRIKLI_OTOBUS": "False",
      "DONUS_ELEKTRIKLI_OTOBUS": "False"
    },
    {
      "_id": 93184,
      "HAT_NO": 877,
      "TARIFE_ID": 3,
      "GIDIS_SAATI": "12:10",
      "DONUS_SAATI": "13:10",
      "SIRA": 4,
      "GIDIS_ENGELLI_DESTEGI": "True",
      "DONUS_ENGELLI_DESTEGI": "True",
      "BISIKLETLI_GIDIS": "True",
      "BISIKLETLI_DONUS": "True",
      "GIDIS_ELEKTRIKLI_OTOBUS": "False",
      "DONUS_ELEKTRIKLI_OTOBUS": "False"
    },
    {
      "_id": 93185,
      "HAT_NO": 877,
      "TARIFE_ID": 3,
      "GIDIS_SAATI": "14:10",
      "DONUS_SAATI": "15:10",
      "SIRA": 5,
      "GIDIS_ENGELLI_DESTEGI": "True",
      "DONUS_ENGELLI_DESTEGI": "True",
      "BISIKLETLI_GIDIS": "True",
      "BISIKLETLI_DONUS": "True",
      "GIDIS_ELEKTRIKLI_OTOBUS": "False",
      "DONUS_ELEKTRIKLI_OTOBUS": "False"
    },
    {
      "_id": 93186,
      "HAT_NO": 877,
      "TARIFE_ID": 3,
      "GIDIS_SAATI": "16:10",
      "DONUS_SAATI": "17:10",
      "SIRA": 6,
      "GIDIS_ENGELLI_DESTEGI": "True",
      "DONUS_ENGELLI_DESTEGI": "True",
      "BISIKLETLI_GIDIS": "True",
      "BISIKLETLI_DONUS": "True",
      "GIDIS_ELEKTRIKLI_OTOBUS": "False",
      "DONUS_ELEKTRIKLI_OTOBUS": "False"
    },
    {
      "_id": 93187,
      "HAT_NO": 877,
      "TARIFE_ID": 3,
      "GIDIS_SAATI": "18:10",
      "DONUS_SAATI": "19:10",
      "SIRA": 7,
      "GIDIS_ENGELLI_DESTEGI": "True",
      "DONUS_ENGELLI_DESTEGI": "True",
      "BISIKLETLI_GIDIS": "True",
      "BISIKLETLI_DONUS": "True",
      "GIDIS_ELEKTRIKLI_OTOBUS": "False",
      "DONUS_ELEKTRIKLI_OTOBUS": "False"
    },
    {
      "_id": 93188,
      "HAT_NO": 877,
      "TARIFE_ID": 1,
      "GIDIS_SAATI": "06:10",
      "DONUS_SAATI": "07:10",
      "SIRA": 1,
      "GIDIS_ENGELLI_DESTEGI": "True",
      "DONUS_ENGELLI_DESTEGI": "True",
      "BISIKLETLI_GIDIS": "False",
      "BISIKLETLI_DONUS": "False",
      "GIDIS_ELEKTRIKLI_OTOBUS": "False",
      "DONUS_ELEKTRIKLI_OTOBUS": "False"
    },
    {
      "_id": 93189,
      "HAT_NO": 877,
      "TARIFE_ID": 1,
      "GIDIS_SAATI": "07:10",
      "DONUS_SAATI": "08:10",
      "SIRA": 2,
      "GIDIS_ENGELLI_DESTEGI": "True",
      "DONUS_ENGELLI_DESTEGI": "True",
      "BISIKLETLI_GIDIS": "True",
      "BISIKLETLI_DONUS": "True",
      "GIDIS_ELEKTRIKLI_OTOBUS": "False",
      "DONUS_ELEKTRIKLI_OTOBUS": "False"
    },
    {
      "_id": 93190,
      "HAT_NO": 877,
      "TARIFE_ID": 1,
      "GIDIS_SAATI": "08:10",
      "DONUS_SAATI": "10:10",
      "SIRA": 3,
      "GIDIS_ENGELLI_DESTEGI": "True",
      "DONUS_ENGELLI_DESTEGI": "True",
      "BISIKLETLI_GIDIS": "False",
      "BISIKLETLI_DONUS": "True",
      "GIDIS_ELEKTRIKLI_OTOBUS": "False",
      "DONUS_ELEKTRIKLI_OTOBUS": "False"
    },
    {
      "_id": 93191,
      "HAT_NO": 877,
      "TARIFE_ID": 1,
      "GIDIS_SAATI": "09:10",
      "DONUS_SAATI": "12:00",
      "SIRA": 4,
      "GIDIS_ENGELLI_DESTEGI": "True",
      "DONUS_ENGELLI_DESTEGI": "True",
      "BISIKLETLI_GIDIS": "True",
      "BISIKLETLI_DONUS": "True",
      "GIDIS_ELEKTRIKLI_OTOBUS": "False",
      "DONUS_ELEKTRIKLI_OTOBUS": "False"
    },
    {
      "_id": 93192,
      "HAT_NO": 877,
      "TARIFE_ID": 1,
      "GIDIS_SAATI": "11:00",
      "DONUS_SAATI": "14:00",
      "SIRA": 5,
      "GIDIS_ENGELLI_DESTEGI": "True",
      "DONUS_ENGELLI_DESTEGI": "True",
      "BISIKLETLI_GIDIS": "True",
      "BISIKLETLI_DONUS": "True",
      "GIDIS_ELEKTRIKLI_OTOBUS": "False",
      "DONUS_ELEKTRIKLI_OTOBUS": "False"
    },
    {
      "_id": 93193,
      "HAT_NO": 877,
      "TARIFE_ID": 1,
      "GIDIS_SAATI": "13:00",
      "DONUS_SAATI": "16:00",
      "SIRA": 6,
      "GIDIS_ENGELLI_DESTEGI": "True",
      "DONUS_ENGELLI_DESTEGI": "True",
      "BISIKLETLI_GIDIS": "True",
      "BISIKLETLI_DONUS": "True",
      "GIDIS_ELEKTRIKLI_OTOBUS": "False",
      "DONUS_ELEKTRIKLI_OTOBUS": "False"
    },
    {
      "_id": 93194,
      "HAT_NO": 877,
      "TARIFE_ID": 1,
      "GIDIS_SAATI": "15:00",
      "DONUS_SAATI": "17:00",
      "SIRA": 7,
      "GIDIS_ENGELLI_DESTEGI": "True",
      "DONUS_ENGELLI_DESTEGI": "True",
      "BISIKLETLI_GIDIS": "True",
      "BISIKLETLI_DONUS": "False",
      "GIDIS_ELEKTRIKLI_OTOBUS": "False",
      "DONUS_ELEKTRIKLI_OTOBUS": "False"
    },
    {
      "_id": 93195,
      "HAT_NO": 877,
      "TARIFE_ID": 1,
      "GIDIS_SAATI": "16:00",
      "DONUS_SAATI": "18:00",
      "SIRA": 8,
      "GIDIS_ENGELLI_DESTEGI": "True",
      "DONUS_ENGELLI_DESTEGI": "True",
      "BISIKLETLI_GIDIS": "False",
      "BISIKLETLI_DONUS": "True",
      "GIDIS_ELEKTRIKLI_OTOBUS": "False",
      "DONUS_ELEKTRIKLI_OTOBUS": "False"
    },
    {
      "_id": 93196,
      "HAT_NO": 877,
      "TARIFE_ID": 1,
      "GIDIS_SAATI": "17:00",
      "DONUS_SAATI": "19:00",
      "SIRA": 9,
      "GIDIS_ENGELLI_DESTEGI": "True",
      "DONUS_ENGELLI_DESTEGI": "True",
      "BISIKLETLI_GIDIS": "True",
      "BISIKLETLI_DONUS": "False",
      "GIDIS_ELEKTRIKLI_OTOBUS": "False",
      "DONUS_ELEKTRIKLI_OTOBUS": "False"
    },
    {
      "_id": 93197,
      "HAT_NO": 877,
      "TARIFE_ID": 1,
      "GIDIS_SAATI": "18:00",
      "DONUS_SAATI": "20:00",
      "SIRA": 10,
      "GIDIS_ENGELLI_DESTEGI": "True",
      "DONUS_ENGELLI_DESTEGI": "True",
      "BISIKLETLI_GIDIS": "False",
      "BISIKLETLI_DONUS": "True",
      "GIDIS_ELEKTRIKLI_OTOBUS": "False",
      "DONUS_ELEKTRIKLI_OTOBUS": "False"
    },
    {
      "_id": 93198,
      "HAT_NO": 877,
      "TARIFE_ID": 1,
      "GIDIS_SAATI": "19:00",
      "DONUS_SAATI": "",
      "SIRA": 11,
      "GIDIS_ENGELLI_DESTEGI": "True",
      "DONUS_ENGELLI_DESTEGI": "False",
      "BISIKLETLI_GIDIS": "True",
      "BISIKLETLI_DONUS": "False",
      "GIDIS_ELEKTRIKLI_OTOBUS": "False",
      "DONUS_ELEKTRIKLI_OTOBUS": "False"
    }
  ]
}
